{
  "routeId": "100100447",
  "collectedAt": "2026-04-06T04:19:47.959Z",
  "stops": [
    {
      "routeId": "100100447",
      "routeNo": "7016",
      "seq": 1,
      "stationId": "111000907",
      "arsId": "35331",
      "name": "은평공영차고지",
      "lat": 37.591802,
      "lng": 126.88381
    },
    {
      "routeId": "100100447",
      "routeNo": "7016",
      "seq": 2,
      "stationId": "111000225",
      "arsId": "12315",
      "name": "덕은교.은평차고지앞",
      "lat": 37.589961128,
      "lng": 126.8834469451
    },
    {
      "routeId": "100100447",
      "routeNo": "7016",
      "seq": 3,
      "stationId": "113000022",
      "arsId": "14112",
      "name": "DMC첨단산업센터",
      "lat": 37.585598,
      "lng": 126.884787
    },
    {
      "routeId": "100100447",
      "routeNo": "7016",
      "seq": 4,
      "stationId": "113000181",
      "arsId": "14272",
      "name": "월드컵파크7단지",
      "lat": 37.581876,
      "lng": 126.878963
    },
    {
      "routeId": "100100447",
      "routeNo": "7016",
      "seq": 5,
      "stationId": "113000020",
      "arsId": "14110",
      "name": "서부면허시험장",
      "lat": 37.5774012358,
      "lng": 126.8802386693
    },
    {
      "routeId": "100100447",
      "routeNo": "7016",
      "seq": 6,
      "stationId": "113000026",
      "arsId": "14116",
      "name": "월드컵파크3단지정문",
      "lat": 37.573822,
      "lng": 126.889228
    },
    {
      "routeId": "100100447",
      "routeNo": "7016",
      "seq": 7,
      "stationId": "113000027",
      "arsId": "14117",
      "name": "월드컵파크2단지.에스플렉스센터",
      "lat": 37.575267,
      "lng": 126.890647
    },
    {
      "routeId": "100100447",
      "routeNo": "7016",
      "seq": 8,
      "stationId": "113000075",
      "arsId": "14166",
      "name": "상암초등학교",
      "lat": 37.576392,
      "lng": 126.893423
    },
    {
      "routeId": "100100447",
      "routeNo": "7016",
      "seq": 9,
      "stationId": "113000074",
      "arsId": "14165",
      "name": "DMC상암센트럴파크",
      "lat": 37.575152,
      "lng": 126.895487
    },
    {
      "routeId": "100100447",
      "routeNo": "7016",
      "seq": 10,
      "stationId": "113000182",
      "arsId": "14273",
      "name": "월드컵경기장북측",
      "lat": 37.572855,
      "lng": 126.899468
    },
    {
      "routeId": "100100447",
      "routeNo": "7016",
      "seq": 11,
      "stationId": "113000072",
      "arsId": "14163",
      "name": "성산아파트",
      "lat": 37.571461,
      "lng": 126.901416
    },
    {
      "routeId": "100100447",
      "routeNo": "7016",
      "seq": 12,
      "stationId": "113000070",
      "arsId": "14161",
      "name": "성산119안전센터",
      "lat": 37.569712,
      "lng": 126.903712
    },
    {
      "routeId": "100100447",
      "routeNo": "7016",
      "seq": 13,
      "stationId": "113000067",
      "arsId": "14158",
      "name": "성산2동주민센터",
      "lat": 37.5677928213,
      "lng": 126.9083263491
    },
    {
      "routeId": "100100447",
      "routeNo": "7016",
      "seq": 14,
      "stationId": "113000066",
      "arsId": "14157",
      "name": "중동초등학교",
      "lat": 37.5666220223,
      "lng": 126.9103076889
    },
    {
      "routeId": "100100447",
      "routeNo": "7016",
      "seq": 15,
      "stationId": "113000094",
      "arsId": "14185",
      "name": "성산2교",
      "lat": 37.5642538566,
      "lng": 126.9124764414
    },
    {
      "routeId": "100100447",
      "routeNo": "7016",
      "seq": 16,
      "stationId": "113000097",
      "arsId": "14188",
      "name": "성미약수터",
      "lat": 37.5624635723,
      "lng": 126.9140662478
    },
    {
      "routeId": "100100447",
      "routeNo": "7016",
      "seq": 17,
      "stationId": "113000099",
      "arsId": "14190",
      "name": "경성중고.홍대부속여중고입구",
      "lat": 37.5596512854,
      "lng": 126.9166140242
    },
    {
      "routeId": "100100447",
      "routeNo": "7016",
      "seq": 18,
      "stationId": "113000102",
      "arsId": "14193",
      "name": "아만티호텔서울",
      "lat": 37.5578790449,
      "lng": 126.9182029073
    },
    {
      "routeId": "100100447",
      "routeNo": "7016",
      "seq": 19,
      "stationId": "113000090",
      "arsId": "14181",
      "name": "서서울농협홍대역점",
      "lat": 37.556592,
      "lng": 126.91971
    },
    {
      "routeId": "100100447",
      "routeNo": "7016",
      "seq": 20,
      "stationId": "113000505",
      "arsId": "14096",
      "name": "홍대입구역(가상)",
      "lat": 37.5552260552,
      "lng": 126.9218643721
    },
    {
      "routeId": "100100447",
      "routeNo": "7016",
      "seq": 21,
      "stationId": "113000422",
      "arsId": "14015",
      "name": "홍대입구역",
      "lat": 37.556641,
      "lng": 126.923466
    },
    {
      "routeId": "100100447",
      "routeNo": "7016",
      "seq": 22,
      "stationId": "113000421",
      "arsId": "14061",
      "name": "동교동삼거리",
      "lat": 37.558069,
      "lng": 126.928546
    },
    {
      "routeId": "100100447",
      "routeNo": "7016",
      "seq": 23,
      "stationId": "113000137",
      "arsId": "14228",
      "name": "신촌역8번출구",
      "lat": 37.555637521,
      "lng": 126.9347610004
    },
    {
      "routeId": "100100447",
      "routeNo": "7016",
      "seq": 24,
      "stationId": "113000077",
      "arsId": "14168",
      "name": "신촌로터리",
      "lat": 37.5538094529,
      "lng": 126.9368825067
    },
    {
      "routeId": "100100447",
      "routeNo": "7016",
      "seq": 25,
      "stationId": "113000080",
      "arsId": "14171",
      "name": "서강대학교",
      "lat": 37.5518272757,
      "lng": 126.9373153932
    },
    {
      "routeId": "100100447",
      "routeNo": "7016",
      "seq": 26,
      "stationId": "113000081",
      "arsId": "14172",
      "name": "광성중고등학교",
      "lat": 37.5493548145,
      "lng": 126.9386715493
    },
    {
      "routeId": "100100447",
      "routeNo": "7016",
      "seq": 27,
      "stationId": "113000083",
      "arsId": "14174",
      "name": "대흥역",
      "lat": 37.5481067455,
      "lng": 126.9409887457
    },
    {
      "routeId": "100100447",
      "routeNo": "7016",
      "seq": 28,
      "stationId": "113000085",
      "arsId": "14176",
      "name": "용강초등학교",
      "lat": 37.546977106,
      "lng": 126.9435145128
    },
    {
      "routeId": "100100447",
      "routeNo": "7016",
      "seq": 29,
      "stationId": "113000087",
      "arsId": "14178",
      "name": "동도중학교.서울디자인고등학교",
      "lat": 37.54564,
      "lng": 126.946768
    },
    {
      "routeId": "100100447",
      "routeNo": "7016",
      "seq": 30,
      "stationId": "113000089",
      "arsId": "14180",
      "name": "공덕역1번출구",
      "lat": 37.5444323434,
      "lng": 126.9493208487
    },
    {
      "routeId": "100100447",
      "routeNo": "7016",
      "seq": 31,
      "stationId": "113000042",
      "arsId": "14132",
      "name": "마포역",
      "lat": 37.5397090071,
      "lng": 126.9457368286
    },
    {
      "routeId": "100100447",
      "routeNo": "7016",
      "seq": 32,
      "stationId": "102000204",
      "arsId": "03298",
      "name": "청암동강변삼성아파트",
      "lat": 37.534015,
      "lng": 126.949323
    },
    {
      "routeId": "100100447",
      "routeNo": "7016",
      "seq": 33,
      "stationId": "102000205",
      "arsId": "03299",
      "name": "원효2동산호아파트",
      "lat": 37.5330177683,
      "lng": 126.9505415559
    },
    {
      "routeId": "100100447",
      "routeNo": "7016",
      "seq": 34,
      "stationId": "102000207",
      "arsId": "03301",
      "name": "원효로풍전아파트",
      "lat": 37.5321286462,
      "lng": 126.9535225314
    },
    {
      "routeId": "100100447",
      "routeNo": "7016",
      "seq": 35,
      "stationId": "102000053",
      "arsId": "03147",
      "name": "원효로3가",
      "lat": 37.5337957151,
      "lng": 126.9583248022
    },
    {
      "routeId": "100100447",
      "routeNo": "7016",
      "seq": 36,
      "stationId": "102000051",
      "arsId": "03145",
      "name": "원효로2가사거리",
      "lat": 37.5349338369,
      "lng": 126.9610704217
    },
    {
      "routeId": "100100447",
      "routeNo": "7016",
      "seq": 37,
      "stationId": "102000049",
      "arsId": "03143",
      "name": "남정초등학교",
      "lat": 37.5363187485,
      "lng": 126.9636632444
    },
    {
      "routeId": "100100447",
      "routeNo": "7016",
      "seq": 38,
      "stationId": "102000048",
      "arsId": "03142",
      "name": "용산e편한세상",
      "lat": 37.53746,
      "lng": 126.965469
    },
    {
      "routeId": "100100447",
      "routeNo": "7016",
      "seq": 39,
      "stationId": "102000297",
      "arsId": "03346",
      "name": "용산꿈나무종합타운",
      "lat": 37.538486933,
      "lng": 126.9672402984
    },
    {
      "routeId": "100100447",
      "routeNo": "7016",
      "seq": 40,
      "stationId": "102000046",
      "arsId": "03140",
      "name": "용산경찰서",
      "lat": 37.5399994643,
      "lng": 126.9690615428
    },
    {
      "routeId": "100100447",
      "routeNo": "7016",
      "seq": 41,
      "stationId": "102000019",
      "arsId": "03111",
      "name": "남영역.민주화운동기념관",
      "lat": 37.541823,
      "lng": 126.972069
    },
    {
      "routeId": "100100447",
      "routeNo": "7016",
      "seq": 42,
      "stationId": "102000009",
      "arsId": "03009",
      "name": "숙대입구역",
      "lat": 37.543295633,
      "lng": 126.9725377982
    },
    {
      "routeId": "100100447",
      "routeNo": "7016",
      "seq": 43,
      "stationId": "102000011",
      "arsId": "03011",
      "name": "갈월동",
      "lat": 37.5509755993,
      "lng": 126.9722373211
    },
    {
      "routeId": "100100447",
      "routeNo": "7016",
      "seq": 44,
      "stationId": "101000007",
      "arsId": "02007",
      "name": "서울역버스환승센터.강우규의거터",
      "lat": 37.555411,
      "lng": 126.972926
    },
    {
      "routeId": "100100447",
      "routeNo": "7016",
      "seq": 45,
      "stationId": "101000033",
      "arsId": "02128",
      "name": "소공동주민센터",
      "lat": 37.562197167,
      "lng": 126.97644367
    },
    {
      "routeId": "100100447",
      "routeNo": "7016",
      "seq": 46,
      "stationId": "101000039",
      "arsId": "02137",
      "name": "서울신문사",
      "lat": 37.5683632936,
      "lng": 126.9773647051
    },
    {
      "routeId": "100100447",
      "routeNo": "7016",
      "seq": 47,
      "stationId": "100000023",
      "arsId": "01118",
      "name": "광화문역2번출구.KT광화문지사",
      "lat": 37.5723209262,
      "lng": 126.9774162769
    },
    {
      "routeId": "100100447",
      "routeNo": "7016",
      "seq": 48,
      "stationId": "100000021",
      "arsId": "01116",
      "name": "경복궁역3번출구",
      "lat": 37.5776713863,
      "lng": 126.9722828893
    },
    {
      "routeId": "100100447",
      "routeNo": "7016",
      "seq": 49,
      "stationId": "100000016",
      "arsId": "01111",
      "name": "통인시장종로구보건소",
      "lat": 37.5805132118,
      "lng": 126.9713851083
    },
    {
      "routeId": "100100447",
      "routeNo": "7016",
      "seq": 50,
      "stationId": "100000017",
      "arsId": "01112",
      "name": "효자동",
      "lat": 37.583091043,
      "lng": 126.9706209712
    },
    {
      "routeId": "100100447",
      "routeNo": "7016",
      "seq": 51,
      "stationId": "100000008",
      "arsId": "01103",
      "name": "경기상고",
      "lat": 37.5871907861,
      "lng": 126.9697701102
    },
    {
      "routeId": "100100447",
      "routeNo": "7016",
      "seq": 52,
      "stationId": "100000045",
      "arsId": "01140",
      "name": "자하문터널입구.석파정",
      "lat": 37.5955575712,
      "lng": 126.9639775924
    },
    {
      "routeId": "100100447",
      "routeNo": "7016",
      "seq": 53,
      "stationId": "100000046",
      "arsId": "01141",
      "name": "하림각",
      "lat": 37.5981476478,
      "lng": 126.962215308
    },
    {
      "routeId": "100100447",
      "routeNo": "7016",
      "seq": 54,
      "stationId": "100000188",
      "arsId": "01286",
      "name": "상명대입구.세검정교회",
      "lat": 37.5994435122,
      "lng": 126.9597921957
    },
    {
      "routeId": "100100447",
      "routeNo": "7016",
      "seq": 55,
      "stationId": "100000180",
      "arsId": "01278",
      "name": "상명대정문",
      "lat": 37.601417,
      "lng": 126.955143
    },
    {
      "routeId": "100100447",
      "routeNo": "7016",
      "seq": 56,
      "stationId": "100000040",
      "arsId": "01135",
      "name": "상명대입구.석파랑",
      "lat": 37.5994133537,
      "lng": 126.958570225
    },
    {
      "routeId": "100100447",
      "routeNo": "7016",
      "seq": 57,
      "stationId": "100000041",
      "arsId": "01136",
      "name": "하림각",
      "lat": 37.5981330665,
      "lng": 126.9617068235
    },
    {
      "routeId": "100100447",
      "routeNo": "7016",
      "seq": 58,
      "stationId": "100000042",
      "arsId": "01137",
      "name": "자하문터널입구.석파정",
      "lat": 37.5955935123,
      "lng": 126.9636434993
    },
    {
      "routeId": "100100447",
      "routeNo": "7016",
      "seq": 59,
      "stationId": "100000006",
      "arsId": "01101",
      "name": "경기상고",
      "lat": 37.5875502159,
      "lng": 126.9693634554
    },
    {
      "routeId": "100100447",
      "routeNo": "7016",
      "seq": 60,
      "stationId": "100000007",
      "arsId": "01102",
      "name": "신교동",
      "lat": 37.5832955233,
      "lng": 126.9702626865
    },
    {
      "routeId": "100100447",
      "routeNo": "7016",
      "seq": 61,
      "stationId": "100000015",
      "arsId": "01110",
      "name": "통인시장종로구보건소",
      "lat": 37.5803257033,
      "lng": 126.9710500404
    },
    {
      "routeId": "100100447",
      "routeNo": "7016",
      "seq": 62,
      "stationId": "100000020",
      "arsId": "01115",
      "name": "경복궁역2번출구",
      "lat": 37.577040144,
      "lng": 126.9721994292
    },
    {
      "routeId": "100100447",
      "routeNo": "7016",
      "seq": 63,
      "stationId": "100000031",
      "arsId": "01126",
      "name": "세종문화회관",
      "lat": 37.573648,
      "lng": 126.976997
    },
    {
      "routeId": "100100447",
      "routeNo": "7016",
      "seq": 64,
      "stationId": "101000290",
      "arsId": "02286",
      "name": "시청앞.덕수궁",
      "lat": 37.5662122834,
      "lng": 126.9768355729
    },
    {
      "routeId": "100100447",
      "routeNo": "7016",
      "seq": 65,
      "stationId": "101000035",
      "arsId": "02132",
      "name": "시청역8번출구",
      "lat": 37.562764205,
      "lng": 126.976148714
    },
    {
      "routeId": "100100447",
      "routeNo": "7016",
      "seq": 66,
      "stationId": "101000003",
      "arsId": "02003",
      "name": "서울역버스환승센터",
      "lat": 37.5551460158,
      "lng": 126.9722570849
    },
    {
      "routeId": "100100447",
      "routeNo": "7016",
      "seq": 67,
      "stationId": "102000012",
      "arsId": "03012",
      "name": "갈월동",
      "lat": 37.5495337218,
      "lng": 126.9717081909
    },
    {
      "routeId": "100100447",
      "routeNo": "7016",
      "seq": 68,
      "stationId": "102000233",
      "arsId": "03327",
      "name": "갈월동.숙대입구역10번출구",
      "lat": 37.5463858567,
      "lng": 126.9716591639
    },
    {
      "routeId": "100100447",
      "routeNo": "7016",
      "seq": 69,
      "stationId": "102000018",
      "arsId": "03110",
      "name": "남영역.민주화운동기념관",
      "lat": 37.542006922,
      "lng": 126.9719271804
    },
    {
      "routeId": "100100447",
      "routeNo": "7016",
      "seq": 70,
      "stationId": "102000045",
      "arsId": "03139",
      "name": "용산경찰서",
      "lat": 37.5405032098,
      "lng": 126.9691858135
    },
    {
      "routeId": "100100447",
      "routeNo": "7016",
      "seq": 71,
      "stationId": "102000047",
      "arsId": "03141",
      "name": "용산꿈나무종합타운.원효로우체국",
      "lat": 37.5386139009,
      "lng": 126.9669290534
    },
    {
      "routeId": "100100447",
      "routeNo": "7016",
      "seq": 72,
      "stationId": "102000050",
      "arsId": "03144",
      "name": "원효로2가",
      "lat": 37.536237441,
      "lng": 126.9629911361
    },
    {
      "routeId": "100100447",
      "routeNo": "7016",
      "seq": 73,
      "stationId": "102000052",
      "arsId": "03146",
      "name": "원효로3가",
      "lat": 37.5340407624,
      "lng": 126.9581798302
    },
    {
      "routeId": "100100447",
      "routeNo": "7016",
      "seq": 74,
      "stationId": "102000208",
      "arsId": "03302",
      "name": "원효로풍전아파트",
      "lat": 37.5323687724,
      "lng": 126.9545135613
    },
    {
      "routeId": "100100447",
      "routeNo": "7016",
      "seq": 75,
      "stationId": "102000206",
      "arsId": "03300",
      "name": "원효2동산호아파트",
      "lat": 37.5331088986,
      "lng": 126.9508277689
    },
    {
      "routeId": "100100447",
      "routeNo": "7016",
      "seq": 76,
      "stationId": "102000203",
      "arsId": "03297",
      "name": "청암동강변삼성아파트",
      "lat": 37.5346144292,
      "lng": 126.9482434807
    },
    {
      "routeId": "100100447",
      "routeNo": "7016",
      "seq": 77,
      "stationId": "113000214",
      "arsId": "14317",
      "name": "강변한신코아",
      "lat": 37.537435,
      "lng": 126.943978
    },
    {
      "routeId": "100100447",
      "routeNo": "7016",
      "seq": 78,
      "stationId": "113000001",
      "arsId": "14001",
      "name": "마포역",
      "lat": 37.540947,
      "lng": 126.947967
    },
    {
      "routeId": "100100447",
      "routeNo": "7016",
      "seq": 79,
      "stationId": "113000088",
      "arsId": "14179",
      "name": "공덕역2번출구",
      "lat": 37.545201,
      "lng": 126.948339
    },
    {
      "routeId": "100100447",
      "routeNo": "7016",
      "seq": 80,
      "stationId": "113000086",
      "arsId": "14177",
      "name": "동도중학교.서울디자인고등학교",
      "lat": 37.5464778856,
      "lng": 126.945401461
    },
    {
      "routeId": "100100447",
      "routeNo": "7016",
      "seq": 81,
      "stationId": "113000084",
      "arsId": "14175",
      "name": "대흥역",
      "lat": 37.547675,
      "lng": 126.94272
    },
    {
      "routeId": "100100447",
      "routeNo": "7016",
      "seq": 82,
      "stationId": "113000082",
      "arsId": "14173",
      "name": "광성중고등학교",
      "lat": 37.548952,
      "lng": 126.93986
    },
    {
      "routeId": "100100447",
      "routeNo": "7016",
      "seq": 83,
      "stationId": "113000079",
      "arsId": "14170",
      "name": "서강대학교",
      "lat": 37.5511,
      "lng": 126.93797
    },
    {
      "routeId": "100100447",
      "routeNo": "7016",
      "seq": 84,
      "stationId": "113000078",
      "arsId": "14169",
      "name": "신촌로터리",
      "lat": 37.5535240112,
      "lng": 126.9372675673
    },
    {
      "routeId": "100100447",
      "routeNo": "7016",
      "seq": 85,
      "stationId": "113000416",
      "arsId": "13021",
      "name": "신촌오거리.현대백화점",
      "lat": 37.5559833987,
      "lng": 126.9345037666
    },
    {
      "routeId": "100100447",
      "routeNo": "7016",
      "seq": 86,
      "stationId": "113000415",
      "arsId": "13019",
      "name": "동교동삼거리",
      "lat": 37.5577646946,
      "lng": 126.92951964
    },
    {
      "routeId": "100100447",
      "routeNo": "7016",
      "seq": 87,
      "stationId": "113000133",
      "arsId": "14224",
      "name": "홍대입구역1번출구",
      "lat": 37.5565612263,
      "lng": 126.9230438058
    },
    {
      "routeId": "100100447",
      "routeNo": "7016",
      "seq": 88,
      "stationId": "113000091",
      "arsId": "14182",
      "name": "동교로사거리",
      "lat": 37.5558462446,
      "lng": 126.9209476216
    },
    {
      "routeId": "100100447",
      "routeNo": "7016",
      "seq": 89,
      "stationId": "113000101",
      "arsId": "14192",
      "name": "아만티호텔서울",
      "lat": 37.5572277306,
      "lng": 126.9193196292
    },
    {
      "routeId": "100100447",
      "routeNo": "7016",
      "seq": 90,
      "stationId": "113000100",
      "arsId": "14191",
      "name": "경성중고.홍대부속여중고입구",
      "lat": 37.5594093604,
      "lng": 126.9172809899
    },
    {
      "routeId": "100100447",
      "routeNo": "7016",
      "seq": 91,
      "stationId": "113000096",
      "arsId": "14187",
      "name": "성미약수터",
      "lat": 37.5617966139,
      "lng": 126.9151050102
    },
    {
      "routeId": "100100447",
      "routeNo": "7016",
      "seq": 92,
      "stationId": "113000095",
      "arsId": "14186",
      "name": "성산2교",
      "lat": 37.5638632409,
      "lng": 126.9132054677
    },
    {
      "routeId": "100100447",
      "routeNo": "7016",
      "seq": 93,
      "stationId": "113000065",
      "arsId": "14156",
      "name": "중동초등학교",
      "lat": 37.5668726108,
      "lng": 126.9104194588
    },
    {
      "routeId": "100100447",
      "routeNo": "7016",
      "seq": 94,
      "stationId": "113000068",
      "arsId": "14159",
      "name": "성산2동주민센터",
      "lat": 37.5680037628,
      "lng": 126.9084370307
    },
    {
      "routeId": "100100447",
      "routeNo": "7016",
      "seq": 95,
      "stationId": "113000069",
      "arsId": "14160",
      "name": "성산119안전센터",
      "lat": 37.5698617774,
      "lng": 126.9038566649
    },
    {
      "routeId": "100100447",
      "routeNo": "7016",
      "seq": 96,
      "stationId": "113000071",
      "arsId": "14162",
      "name": "성산아파트",
      "lat": 37.571597138,
      "lng": 126.9014985417
    },
    {
      "routeId": "100100447",
      "routeNo": "7016",
      "seq": 97,
      "stationId": "113000183",
      "arsId": "14274",
      "name": "월드컵경기장북측",
      "lat": 37.573967,
      "lng": 126.898104
    },
    {
      "routeId": "100100447",
      "routeNo": "7016",
      "seq": 98,
      "stationId": "113000202",
      "arsId": "14296",
      "name": "디지털미디어시티역2번출구",
      "lat": 37.5752078233,
      "lng": 126.8996741287
    },
    {
      "routeId": "100100447",
      "routeNo": "7016",
      "seq": 99,
      "stationId": "113000073",
      "arsId": "14164",
      "name": "DMC상암센트럴파크",
      "lat": 37.575185,
      "lng": 126.89604
    },
    {
      "routeId": "100100447",
      "routeNo": "7016",
      "seq": 100,
      "stationId": "113000076",
      "arsId": "14167",
      "name": "상암초등학교",
      "lat": 37.576549,
      "lng": 126.89372
    },
    {
      "routeId": "100100447",
      "routeNo": "7016",
      "seq": 101,
      "stationId": "113000028",
      "arsId": "14118",
      "name": "월드컵파크2단지.에스플렉스센터",
      "lat": 37.5753384971,
      "lng": 126.8902909609
    },
    {
      "routeId": "100100447",
      "routeNo": "7016",
      "seq": 102,
      "stationId": "113000017",
      "arsId": "14107",
      "name": "월드컵파크3단지.난지천공원",
      "lat": 37.573349,
      "lng": 126.887954
    },
    {
      "routeId": "100100447",
      "routeNo": "7016",
      "seq": 103,
      "stationId": "113000019",
      "arsId": "14109",
      "name": "서부면허시험장",
      "lat": 37.5778826192,
      "lng": 126.880437164
    },
    {
      "routeId": "100100447",
      "routeNo": "7016",
      "seq": 104,
      "stationId": "113000180",
      "arsId": "14271",
      "name": "월드컵파크7단지",
      "lat": 37.5811497135,
      "lng": 126.8784199476
    },
    {
      "routeId": "100100447",
      "routeNo": "7016",
      "seq": 105,
      "stationId": "113000021",
      "arsId": "14111",
      "name": "DMC첨단산업센터",
      "lat": 37.585347,
      "lng": 126.885192
    },
    {
      "routeId": "100100447",
      "routeNo": "7016",
      "seq": 106,
      "stationId": "111000224",
      "arsId": "12314",
      "name": "덕은교.은평차고지앞",
      "lat": 37.5885944751,
      "lng": 126.8856592313
    }
  ]
}